cityfront/__init__.py
cityfront/auth/__init__.py
cityfront/auth/_url.py
cityfront/auth/action.py
cityfront/auth/app.py
cityfront/auth/base.py
cityfront/auth/cookie.py
cityfront/auth/jwt.py
cityfront/auth/key.py
cityfront/auth/oauth.py
cityfront/auth/token.py
cityfront/auth/unauth.py
cityfront/cache/__init__.py
cityfront/cache/base.py
cityfront/cache/mem_cache.py
cityfront/cli.py
cityfront/client.py
cityfront/config.py
cityfront/constants.py
cityfront/core.py
cityfront/exception.py
cityfront/generator/__init__.py
cityfront/generator/config.py
cityfront/generator/god_file.py
cityfront/generator/log.py
cityfront/generator/models.py
cityfront/generator/parser.py
cityfront/generator/parsers/__init__.py
cityfront/generator/parsers/data.py
cityfront/generator/parsers/endpoints/__init__.py
cityfront/generator/parsers/endpoints/endpoint.py
cityfront/generator/parsers/endpoints/parameter.py
cityfront/generator/parsers/endpoints/request_body.py
cityfront/generator/parsers/endpoints/response.py
cityfront/generator/parsers/schemas/__init__.py
cityfront/generator/parsers/schemas/any_schema.py
cityfront/generator/parsers/schemas/bool_schema.py
cityfront/generator/parsers/schemas/enum_schema.py
cityfront/generator/parsers/schemas/float_schema.py
cityfront/generator/parsers/schemas/int_schema.py
cityfront/generator/parsers/schemas/list_schema.py
cityfront/generator/parsers/schemas/model_schema.py
cityfront/generator/parsers/schemas/none_schema.py
cityfront/generator/parsers/schemas/schema.py
cityfront/generator/parsers/schemas/string_schema.py
cityfront/generator/parsers/schemas/union_schema.py
cityfront/generator/parsers/utils.py
cityfront/generator/source.py
cityfront/paginator.py
cityfront/py.typed
cityfront/response.py
cityfront/rest/__init__.py
cityfront/rest/account.py
cityfront/rest/avatars.py
cityfront/rest/databases.py
cityfront/rest/functions.py
cityfront/rest/health.py
cityfront/rest/locale.py
cityfront/rest/models.py
cityfront/rest/projects.py
cityfront/rest/storage.py
cityfront-1.0.0.dist-info/WHEEL
cityfront-1.0.0.dist-info/METADATA
cityfront-1.0.0.dist-info/RECORD
